materialy/__init__.py
materialy/_version.py
materialy/emoji.py
mkdocs_material_extensions_2-1.0.0.dist-info/LICENSE
mkdocs_material_extensions_2-1.0.0.dist-info/METADATA
mkdocs_material_extensions_2-1.0.0.dist-info/WHEEL
mkdocs_material_extensions_2-1.0.0.dist-info/top_level.txt
mkdocs_material_extensions_2-1.0.0.dist-info/RECORD
