Metadata-Version: 2.1
Name: mkdocs-material-extensions-2
Version: 1.0.0
Summary: Extension pack for Python Markdown and MkDocs Material.
Author-email: Zhiyuan Chen <this@zyc.ai>
Maintainer-email: Zhiyuan Chen <this@zyc.ai>
License: GNU AFFERO GENERAL PUBLIC LICENSE
Project-URL: documentation, https://materialy.danling.org
Project-URL: homepage, https://materialy.danling.org
Project-URL: repository, https://github.com/ZhiyuanChen/mkdocs-material-extensions-2
Keywords: extensions,markdown,mkdocs
Classifier: Development Status :: 2 - Pre-Alpha 
Classifier: Intended Audience :: Developers
Classifier: Intended Audience :: Education
Classifier: Intended Audience :: Science/Research
Classifier: License :: OSI Approved :: GNU Affero General Public License v3 or later (AGPLv3+)
Classifier: Operating System :: OS Independent
Classifier: Programming Language :: Python :: 3 :: Only
Classifier: Programming Language :: Python :: 3.7
Classifier: Programming Language :: Python :: 3.8
Classifier: Programming Language :: Python :: 3.9
Classifier: Programming Language :: Python :: 3.10
Classifier: Programming Language :: Python :: 3.11
Classifier: Programming Language :: Python :: 3.12
Classifier: Topic :: Scientific/Engineering :: Artificial Intelligence
Requires-Python: >=3.7
License-File: LICENSE
Requires-Dist: mkdocs-material
